allie_sdk/__init__.py
allie_sdk/alation.py
allie_sdk/core/__init__.py
allie_sdk/core/async_handler.py
allie_sdk/core/custom_exceptions.py
allie_sdk/core/data_structures.py
allie_sdk/core/logs.py
allie_sdk/core/request_handler.py
allie_sdk/methods/__init__.py
allie_sdk/methods/authentication.py
allie_sdk/methods/business_policy.py
allie_sdk/methods/connector.py
allie_sdk/methods/custom_field.py
allie_sdk/methods/custom_template.py
allie_sdk/methods/data_dictionary.py
allie_sdk/methods/data_quality.py
allie_sdk/methods/dataflow.py
allie_sdk/methods/datasource.py
allie_sdk/methods/document.py
allie_sdk/methods/document_hub_folder.py
allie_sdk/methods/domain.py
allie_sdk/methods/glossary_term.py
allie_sdk/methods/group.py
allie_sdk/methods/job.py
allie_sdk/methods/otype.py
allie_sdk/methods/policy_group.py
allie_sdk/methods/query.py
allie_sdk/methods/rdbms.py
allie_sdk/methods/trust_check.py
allie_sdk/methods/user.py
allie_sdk/methods/virtual_datasource.py
allie_sdk/methods/virtual_filesystem.py
allie_sdk/methods/visual_config.py
allie_sdk/models/__init__.py
allie_sdk/models/authentication_model.py
allie_sdk/models/business_policy_model.py
allie_sdk/models/connector_model.py
allie_sdk/models/custom_field_model.py
allie_sdk/models/custom_template_model.py
allie_sdk/models/data_dictionary_model.py
allie_sdk/models/data_quality_model.py
allie_sdk/models/dataflow_model.py
allie_sdk/models/datasource_model.py
allie_sdk/models/document_hub_folder_model.py
allie_sdk/models/document_model.py
allie_sdk/models/domain_model.py
allie_sdk/models/glossary_term_model.py
allie_sdk/models/group_model.py
allie_sdk/models/job_model.py
allie_sdk/models/otype_model.py
allie_sdk/models/policy_group_model.py
allie_sdk/models/query_model.py
allie_sdk/models/rdbms_model.py
allie_sdk/models/trust_check_model.py
allie_sdk/models/user_model.py
allie_sdk/models/virtual_datasource_model.py
allie_sdk/models/virtual_filesystem_model.py
allie_sdk/models/visual_config_model.py
allie_sdk-2.2.0.dist-info/METADATA
allie_sdk-2.2.0.dist-info/WHEEL
allie_sdk-2.2.0.dist-info/licenses/LICENSE
allie_sdk-2.2.0.dist-info/RECORD
