Metadata-Version: 2.4
Name: allie-sdk
Version: 2.2.0
Summary: A Python library for the Alation REST APIs.
Project-URL: Homepage, https://github.com/Alation/Allie-SDK
Project-URL: Issues, https://github.com/Alation/Allie-SDK/issues
Project-URL: Documentation, https://alation.github.io/Allie-SDK/
Author-email: Mario Aburto <mario.aburto@alation.com>, Diethard Steiner <diethard.steiner@alation.com>, Jon Lanham <jon.lanham@alation.com>, Radek Ignaszewski <radek.ignaszewski@alation.com>
Maintainer-email: Mario Aburto <mario.aburto@alation.com>, Diethard Steiner <diethard.steiner@alation.com>, Jon Lanham <jon.lanham@alation.com>, Radek Ignaszewski <radek.ignaszewski@alation.com>
License:                                  Apache License
License-File: LICENSE
Keywords: Alation,Alation Python SDK,Alation SDK,Allie SDK
Classifier: License :: OSI Approved :: Apache Software License
Classifier: Operating System :: OS Independent
Classifier: Programming Language :: Python :: 3
Requires-Python: >=3.10
Requires-Dist: python-dateutil~=2.8.2
Requires-Dist: python-json-logger~=2.0.4
Requires-Dist: requests~=2.32.0
